{
    "name": "Past tense 1",
    "type": "flashcards",
    "lesson_id": null,
    "sentences": [
        { "base_language": "I was happy.", "target_language": "Yo estuve feliz." },
        { "base_language": "You were happy.", "target_language": "Tú estuviste feliz." },
        { "base_language": "He was happy.", "target_language": "Él estuvo feliz." },
        { "base_language": "I was sad.", "target_language": "Yo estuve triste." },
        { "base_language": "You were sad.", "target_language": "Tú estuviste triste." },
        { "base_language": "She was sad.", "target_language": "Ella estuvo triste." },
        { "base_language": "I was in love.", "target_language": "Yo estuve enamorado/enamorada." },
        { "base_language": "You were in love.", "target_language": "Tú estuviste enamorado/enamorada." },
        { "base_language": "He was in love.", "target_language": "Él estuvo enamorado." },
        { "base_language": "I was full of joy.", "target_language": "Yo estuve lleno/llena de alegría." },
        { "base_language": "You were full of joy.", "target_language": "Tú estuviste lleno/llena de alegría." },
        { "base_language": "She was full of joy.", "target_language": "Ella estuvo llena de alegría." },
        { "base_language": "I was angry.", "target_language": "Yo estuve enfadado/enfadada." },
        { "base_language": "You were angry.", "target_language": "Tú estuviste enfadado/enfadada." },
        { "base_language": "He was angry.", "target_language": "Él estuvo enfadado." },
        { "base_language": "I was afraid.", "target_language": "Yo tuve miedo." },
        { "base_language": "You were afraid.", "target_language": "Tú tuviste miedo." },
        { "base_language": "She was afraid.", "target_language": "Ella tuvo miedo." },
        { "base_language": "I was hopeful.", "target_language": "Yo tuve esperanza." },
        { "base_language": "You were hopeful.", "target_language": "Tú tuviste esperanza." },
        { "base_language": "He was hopeful.", "target_language": "Él tuvo esperanza." },
        { "base_language": "I was stressed.", "target_language": "Yo estuve estresado/estresada." },
        { "base_language": "You were stressed.", "target_language": "Tú estuviste estresado/estresada." },
        { "base_language": "She was stressed.", "target_language": "Ella estuvo estresada." },
        { "base_language": "I was in a bad mood.", "target_language": "Yo estuve de mal humor." },
        { "base_language": "You were in a bad mood.", "target_language": "Tú estuviste de mal humor." },
        { "base_language": "He was in a bad mood.", "target_language": "Él estuvo de mal humor." },
        { "base_language": "I was feeling happy.", "target_language": "Yo me sentí feliz." },
        { "base_language": "You were feeling happy.", "target_language": "Tú te sentiste feliz." },
        { "base_language": "She was feeling happy.", "target_language": "Ella se sintió feliz." },
        { "base_language": "I was emotional.", "target_language": "Yo fui emocional." },
        { "base_language": "You were emotional.", "target_language": "Tú fuiste emocional." },
        { "base_language": "He was emotional.", "target_language": "Él fue emocional." },
        { "base_language": "I was excited.", "target_language": "Yo estuve emocionado/emocionada." },
        { "base_language": "You were excited.", "target_language": "Tú estuviste emocionado/emocionada." },
        { "base_language": "She was excited.", "target_language": "Ella estuvo emocionada." },
        { "base_language": "I was proud.", "target_language": "Yo estuve orgulloso/orgullosa." },
        { "base_language": "You were proud.", "target_language": "Tú estuviste orgulloso/orgullosa." },
        { "base_language": "He was proud.", "target_language": "Él estuvo orgulloso." },
        { "base_language": "I was ashamed.", "target_language": "Yo estuve avergonzado/avergonzada." },
        { "base_language": "You were ashamed.", "target_language": "Tú estuviste avergonzado/avergonzada." },
        { "base_language": "She was ashamed.", "target_language": "Ella estuvo avergonzada." },
        { "base_language": "I was guilty.", "target_language": "Yo me sentí culpable." },
        { "base_language": "You were guilty.", "target_language": "Tú te sentiste culpable." },
        { "base_language": "He was guilty.", "target_language": "Él se sintió culpable." },
        { "base_language": "I was envious.", "target_language": "Yo estuve envidioso/envidiosa." },
        { "base_language": "You were envious.", "target_language": "Tú estuviste envidioso/envidiosa." },
        { "base_language": "She was envious.", "target_language": "Ella estuvo envidiosa." },
        { "base_language": "I was jealous.", "target_language": "Yo estuve celoso/celosa." },
        { "base_language": "You were jealous.", "target_language": "Tú estuviste celoso/celosa." },
        { "base_language": "He was jealous.", "target_language": "Él estuvo celoso." },
        { "base_language": "I was calm.", "target_language": "Yo estuve tranquilo/tranquila." },
        { "base_language": "You were calm.", "target_language": "Tú estuviste tranquilo/tranquila." },
        { "base_language": "She was calm.", "target_language": "Ella estuvo tranquila." },
        { "base_language": "I was at peace.", "target_language": "Yo estuve en paz." },
        { "base_language": "You were at peace.", "target_language": "Tú estuviste en paz." },
        { "base_language": "He was at peace.", "target_language": "Él estuvo en paz." },
        { "base_language": "I was anxious.", "target_language": "Yo estuve ansioso/ansiosa." },
        { "base_language": "You were anxious.", "target_language": "Tú estuviste ansioso/ansiosa." },
        { "base_language": "She was anxious.", "target_language": "Ella estuvo ansiosa." },
        { "base_language": "I was worried.", "target_language": "Yo estuve preocupado/preocupada." },
        { "base_language": "You were worried.", "target_language": "Tú estuviste preocupado/preocupada." },
        { "base_language": "He was worried.", "target_language": "Él estuvo preocupado." },
        { "base_language": "I was panicked.", "target_language": "Yo estuve en pánico." },
        { "base_language": "You were panicked.", "target_language": "Tú estuviste en pánico." },
        { "base_language": "She was panicked.", "target_language": "Ella estuvo en pánico." },
        { "base_language": "I was disgusted.", "target_language": "Yo estuve disgustado/disgustada." },
        { "base_language": "You were disgusted.", "target_language": "Tú estuviste disgustado/disgustada." },
        { "base_language": "He was disgusted.", "target_language": "Él estuvo disgustado." },
        { "base_language": "I was surprised.", "target_language": "Yo estuve sorprendido/sorprendida." },
        { "base_language": "You were surprised.", "target_language": "Tú estuviste sorprendido/sorprendida." },
        { "base_language": "She was surprised.", "target_language": "Ella estuvo sorprendida." },
        { "base_language": "I was shocked.", "target_language": "Yo estuve conmocionado/conmocionada." },
        { "base_language": "You were shocked.", "target_language": "Tú estuviste conmocionado/conmocionada." },
        { "base_language": "He was shocked.", "target_language": "Él estuvo conmocionado." },
        { "base_language": "I was passionate.", "target_language": "Yo fui apasionado/apasionada." },
        { "base_language": "You were passionate.", "target_language": "Tú fuiste apasionado/apasionada." },
        { "base_language": "She was passionate.", "target_language": "Ella fue apasionada." }
    ]
}