{
    "name": "Common Places",
    "image": "/picture-lessons/commonPlaces.jpg",
    "dots": [
        {
            "top": "14%",
            "left": "12%",
            "sentences": [
                {
                    "base_language": "This is the university with its iconic clock tower.",
                    "target_language": "这是大学，有标志性的钟楼。"
                }
            ]
        },
        {
            "top": "18%",
            "left": "42%",
            "sentences": [
                {
                    "base_language": "This large building is a government or civic center.",
                    "target_language": "这栋大楼是政府办公楼或市民中心。"
                }
            ]
        },
        {
            "top": "22%",
            "left": "72%",
            "sentences": [
                {
                    "base_language": "The hospital has a red cross sign out front.",
                    "target_language": "医院门前有红十字标志。"
                }
            ]
        },
        {
            "top": "42%",
            "left": "30%",
            "sentences": [
                {
                    "base_language": "This is the bank.",
                    "target_language": "这是银行。"
                }
            ]
        },
        {
            "top": "38%",
            "left": "65%",
            "sentences": [
                {
                    "base_language": "This restaurant has a striped awning over the entrance.",
                    "target_language": "这家餐厅入口处有一个条纹遮阳篷。"
                }
            ]
        },
        {
            "top": "42%",
            "left": "80%",
            "sentences": [
                {
                    "base_language": "This is the market with open stalls selling goods.",
                    "target_language": "这是市场，有摆放商品的露天摊位。"
                }
            ]
        },
        {
            "top": "55%",
            "left": "50%",
            "sentences": [
                {
                    "base_language": "This domed building is a theater or cultural hall.",
                    "target_language": "这座圆顶建筑是剧院或文化大厅。"
                }
            ]
        },
        {
            "top": "60%",
            "left": "75%",
            "sentences": [
                {
                    "base_language": "A tram is passing through the city.",
                    "target_language": "一辆有轨电车正穿越城市。"
                }
            ]
        },
        {
            "top": "68%",
            "left": "22%",
            "sentences": [
                {
                    "base_language": "There is a park with beautiful cherry blossom trees.",
                    "target_language": "公园里有美丽的樱花树。"
                }
            ]
        },
        {
            "top": "72%",
            "left": "28%",
            "sentences": [
                {
                    "base_language": "There is a fountain in the park plaza.",
                    "target_language": "公园广场中央有一座喷泉。"
                }
            ]
        },
        {
            "top": "82%",
            "left": "8%",
            "sentences": [
                {
                    "base_language": "The beach and waterfront area are at the edge of the city.",
                    "target_language": "海滩和滨水区位于城市边缘。"
                }
            ]
        },
        {
            "top": "85%",
            "left": "72%",
            "sentences": [
                {
                    "base_language": "This large dome is an observatory or museum.",
                    "target_language": "这个大圆顶建筑是天文台或博物馆。"
                }
            ]
        },
        {
            "top": "50%",
            "left": "42%",
            "sentences": [
                {
                    "base_language": "This is a crosswalk at a street intersection.",
                    "target_language": "这是路口的人行横道。"
                }
            ]
        }
    ]
}
